setup.py
udacity_distributions_01/Binomialdistribution.py
udacity_distributions_01/Gaussiandistribution.py
udacity_distributions_01/Generaldistribution.py
udacity_distributions_01/__init__.py
udacity_distributions_01.egg-info/PKG-INFO
udacity_distributions_01.egg-info/SOURCES.txt
udacity_distributions_01.egg-info/dependency_links.txt
udacity_distributions_01.egg-info/not-zip-safe
udacity_distributions_01.egg-info/top_level.txt