Metadata-Version: 1.0
Name: udacity-distributions-01
Version: 0.1
Summary: Gaussian distributions
Home-page: UNKNOWN
Author: Mayank Amble
Author-email: amblemayank@gmail.com
License: UNKNOWN
Platform: UNKNOWN
